allsafe/__init__.py
allsafe/main.py
allsafe/modules/__init__.py
allsafe/modules/console_stream.py
allsafe/modules/encryption.py
allsafe/modules/utils.py
allsafe-1.5.2.dist-info/licenses/LICENSE.txt
allsafe-1.5.2.dist-info/METADATA
allsafe-1.5.2.dist-info/WHEEL
allsafe-1.5.2.dist-info/entry_points.txt
allsafe-1.5.2.dist-info/top_level.txt
allsafe-1.5.2.dist-info/RECORD
