Metadata-Version: 2.4
Name: AllSafe
Version: 1.5.2
Summary: AllSafe, A Modern Password Generator
Home-page: https://github.com/emargi/AllSafe
Author: Mohamad Reza
Project-URL: Source Code, https://github.com/emargi/Allsafe#readme
Project-URL: Bug Tracker, https://github.com/emargi/AllSafe/issues
Keywords: password password-generator tool allsafe generator
Classifier: Programming Language :: Python :: 3
Classifier: License :: OSI Approved :: MIT License
Classifier: Operating System :: OS Independent
Classifier: Environment :: Console
Classifier: Topic :: Security
License-File: LICENSE.txt
Requires-Dist: rich==13.9.4
Dynamic: author
Dynamic: classifier
Dynamic: description
Dynamic: description-content-type
Dynamic: home-page
Dynamic: keywords
Dynamic: license-file
Dynamic: project-url
Dynamic: requires-dist
Dynamic: summary
